pdcleaner/__init__.py
pdcleaner/package.py
pdcleaner-1.0.8.dist-info/METADATA
pdcleaner-1.0.8.dist-info/WHEEL
pdcleaner-1.0.8.dist-info/top_level.txt
pdcleaner-1.0.8.dist-info/RECORD
