Metadata-Version: 2.4
Name: pdcleaner
Version: 1.0.8
Summary: 修复了功能：新增将None替换成空字符串
Home-page: https://gitee.com/manjim/pdcleaner
Author: Your Name
Author-email: your.email@example.com
Classifier: Programming Language :: Python :: 3
Classifier: License :: OSI Approved :: MIT License
Classifier: Operating System :: OS Independent
Requires-Python: >=3.6
Requires-Dist: pandas
Dynamic: author
Dynamic: author-email
Dynamic: classifier
Dynamic: home-page
Dynamic: requires-dist
Dynamic: requires-python
Dynamic: summary
